markus_ai_server/__init__.py
markus_ai_server/__main__.py
markus_ai_server/redis_helper.py
markus_ai_server/server.py
markus_ai_server-0.1.0.dist-info/licenses/LICENSE
markus_ai_server-0.1.0.dist-info/WHEEL
markus_ai_server-0.1.0.dist-info/METADATA
markus_ai_server-0.1.0.dist-info/RECORD
